MANIFEST.in
README.rst
setup.py
sg/__init__.py
sg/archive.py
sg/helper.py
sg/job.py
sg/resource.py
sg/vault.py
sg/resources/README.rst
sg/resources/requirements.txt
sg/resources/scripts/sg-vault-delete
synchronous_glacier.egg-info/PKG-INFO
synchronous_glacier.egg-info/SOURCES.txt
synchronous_glacier.egg-info/dependency_links.txt
synchronous_glacier.egg-info/not-zip-safe
synchronous_glacier.egg-info/requires.txt
synchronous_glacier.egg-info/top_level.txt