Metadata-Version: 1.0
Name: synchronous-glacier
Version: 0.2.0
Summary: Execute workflows against Glacier.
Home-page: https://github.com/dsoprea/PySynchronousGlacier
Author: Dustin Oprea
Author-email: dustin@randomingenuity.com
License: GPL 2
Keywords: aws glacier
Platform: UNKNOWN
